array_range.py
array_range-1.0.dist-info/METADATA
array_range-1.0.dist-info/WHEEL
array_range-1.0.dist-info/top_level.txt
array_range-1.0.dist-info/zip-safe
array_range-1.0.dist-info/RECORD
