Metadata-Version: 2.1
Name: array-range
Version: 1.0
Summary: Generate tuples of slices to easily iterate on non-overlapping sub-arrays of multdimensional arrays
Home-page: https://github.com/fasiha/array_ranges
Author: Ahmed Fasih
Author-email: ahmed@aldebrn.me
License: Unlicense
Platform: UNKNOWN
